malwareclassify-0.1.0.dist-info/METADATA
malwareclassify-0.1.0.dist-info/WHEEL
malwareclassify/__init__.py
malwareclassify/_core.abi3.so
malwareclassify/_core.pyi
malwareclassify/model/__init__.py
malwareclassify/model/logit.py
malwareclassify/py.typed
malwareclassify-0.1.0.dist-info/RECORD
