Metadata-Version: 2.4
Name: malwareclassify
Version: 0.1.0
Requires-Dist: matplotlib>=3.10.7
Requires-Dist: numpy>=2.3.5
Requires-Dist: polars>=1.35.2
Requires-Dist: scikit-learn>=1.7.2
Requires-Dist: scipy>=1.16.3
Requires-Dist: torch>=2.9.1
Requires-Dist: twine>=6.2.0
Summary: Add your description here
Author-email: radioactiveshrimp <radioactiveshrimpmail@gmail.com>
Requires-Python: >=3.12
